pcservices_package/__init__.py
pcservices_package/campaign/__init__.py
pcservices_package/campaign/utils.py
pcservices_package/data_transfer/__init__.py
pcservices_package/data_transfer/transfer.py
pcservices_package/pyspark/__init__.py
pcservices_package/pyspark/toolkit.py
pcservices_package/spark_helpers.py
pcservices_package-0.1.3.dist-info/METADATA
pcservices_package-0.1.3.dist-info/WHEEL
pcservices_package-0.1.3.dist-info/RECORD
