Metadata-Version: 2.1
Name: pcservices-package
Version: 0.1.3
Summary: A package for PCF&S data processing in Python and Pyspark
License: MIT
Author: Gang Huang
Author-email: gang.huang@loblaw.ca
Requires-Python: >=3.10,<4.0
Classifier: License :: OSI Approved :: MIT License
Classifier: Programming Language :: Python :: 3
Classifier: Programming Language :: Python :: 3.10
Classifier: Programming Language :: Python :: 3.11
Classifier: Programming Language :: Python :: 3.12
Classifier: Programming Language :: Python :: 3.13
Requires-Dist: pandas (>=2.3.0)
